ascacou-0.3.1.dist-info/METADATA
ascacou-0.3.1.dist-info/WHEEL
ascacou/__init__.py
ascacou/ascacou.cpython-39-darwin.so
ascacou-0.3.1.dist-info/RECORD
